semhue
