Metadata-Version: 2.1
Name: semhue
Version: 1.1.6
Summary: UNKNOWN
Home-page: https://github.com/semmoolenschot/semhue
Author: Sem Moolenschot
Author-email: 
License: MIT
Platform: UNKNOWN
Classifier: Programming Language :: Python :: 3
Classifier: License :: OSI Approved :: MIT License
Classifier: Operating System :: OS Independent
